otter_service/__init__.py
otter_service/access_sops_keys.py
otter_service/grade_assignment.py
otter_service/otter_nb.py
otter_service/util.py
otter_service/secrets/gh_key.yaml
otter_service/secrets/gke_key.yaml
otter_service-2.0.4.dist-info/licenses/LICENSE
otter_service-2.0.4.dist-info/METADATA
otter_service-2.0.4.dist-info/WHEEL
otter_service-2.0.4.dist-info/entry_points.txt
otter_service-2.0.4.dist-info/top_level.txt
otter_service-2.0.4.dist-info/RECORD
