Metadata-Version: 2.4
Name: otter_service
Version: 2.0.4
Summary: Grading Service for Edx 8x courses
Home-page: https://github.com/data-8/otter-service
Author: Vincent Su and Sean Morris
Author-email: sean.smorris@berkeley.edu
Classifier: Programming Language :: Python :: 3
Classifier: License :: OSI Approved :: MIT License
Classifier: Operating System :: OS Independent
Requires-Python: >=3.8
License-File: LICENSE
Dynamic: license-file
